fast_downward/__init__.py
fast_downward/interface.py
fast_downward/libdownward.so
fast_downward/driver/__init__.py
fast_downward/driver/aliases.py
fast_downward/driver/arguments.py
fast_downward/driver/call.py
fast_downward/driver/cleanup.py
fast_downward/driver/limits.py
fast_downward/driver/main.py
fast_downward/driver/plan_manager.py
fast_downward/driver/portfolio_runner.py
fast_downward/driver/returncodes.py
fast_downward/driver/run_components.py
fast_downward/driver/tests.py
fast_downward/driver/util.py
fast_downward/driver/version.py
fast_downward/translate/__init__.py
fast_downward/translate/axiom_rules.py
fast_downward/translate/build_model.py
fast_downward/translate/constraints.py
fast_downward/translate/fact_groups.py
fast_downward/translate/graph.py
fast_downward/translate/greedy_join.py
fast_downward/translate/instantiate.py
fast_downward/translate/invariant_finder.py
fast_downward/translate/invariants.py
fast_downward/translate/normalize.py
fast_downward/translate/options.py
fast_downward/translate/pddl_to_prolog.py
fast_downward/translate/sas_tasks.py
fast_downward/translate/sccs.py
fast_downward/translate/simplify.py
fast_downward/translate/split_rules.py
fast_downward/translate/timers.py
fast_downward/translate/tools.py
fast_downward/translate/translate.py
fast_downward/translate/variable_order.py
fast_downward/translate/pddl/__init__.py
fast_downward/translate/pddl/actions.py
fast_downward/translate/pddl/axioms.py
fast_downward/translate/pddl/conditions.py
fast_downward/translate/pddl/effects.py
fast_downward/translate/pddl/f_expression.py
fast_downward/translate/pddl/functions.py
fast_downward/translate/pddl/pddl_types.py
fast_downward/translate/pddl/predicates.py
fast_downward/translate/pddl/tasks.py
fast_downward/translate/pddl_parser/__init__.py
fast_downward/translate/pddl_parser/lisp_parser.py
fast_downward/translate/pddl_parser/parsing_functions.py
fast_downward/translate/pddl_parser/pddl_file.py
fast_downward/translate/tests/__init__.py
fast_downward_textworld-20.6.3.dist-info/licenses/LICENSE.md
fast_downward_textworld-20.6.3.dist-info/METADATA
fast_downward_textworld-20.6.3.dist-info/WHEEL
fast_downward_textworld-20.6.3.dist-info/top_level.txt
fast_downward_textworld-20.6.3.dist-info/RECORD
