Metadata-Version: 2.4
Name: fast_downward_textworld
Version: 20.6.3
Summary: Fast-Downward for TextWorld
Home-page: https://github.com/MarcCote/downward
Author: Marc-Alexandre Côté
License: ### GNU GENERAL PUBLIC LICENSE
License-File: LICENSE.md
Dynamic: author
Dynamic: description
Dynamic: description-content-type
Dynamic: home-page
Dynamic: license
Dynamic: license-file
Dynamic: summary
